Workbook
Name Slicer_Category: #N/A
Name Slicer_Year: #N/A

Sheet Dashboard
B2: PT. Sejahtera Bersama Sales Dashboard
B4: Periode Januari 2020 - Desember 2021
M7: TOTAL REVENUE | W7: TOTAL ORDER | AG7: UNIT TERJUAL | AQ7: PELANGGAN AKTIF | BA7: RATA-RATA NILAI ORDER | BK7: REPEAT CUSTOMER RATE
M8: =GETPIVOTDATA("[Measures].[Total Revenue]",Pivot!$A$1) -> 1754750.6 | W8: =GETPIVOTDATA("[Measures].[Total Order]",Pivot!$A$1) -> 3339 | AG8: =GETPIVOTDATA("[Measures].[Unit Terjual]",Pivot!$A$1) -> 11654 | AQ8: =GETPIVOTDATA("[Measures].[Pelanggan Aktif]",Pivot!$A$1) -> 1671 | BA8: =GETPIVOTDATA("[Measures].[Avg Order Value]",Pivot!$A$1) -> 525.53177 | BK8: =GETPIVOTDATA("[Measures].[Repeat Rate]",Pivot!$A$1) -> 0.59066427

Sheet Pivot
A1: Values
A2: Total Revenue | B2: 1754750.6
A3: Total Order | B3: 3339
A4: Unit Terjual | B4: 11654
A5: Pelanggan Aktif | B5: 1671
A6: Avg Order Value | B6: 525.53177
A7: Repeat Rate | B7: 0.59066427
A9: Sum of Revenue | B9: Column Labels | F9: Row Labels | G9: Sum of Revenue | I9: Row Labels | J9: Sum of Revenue | L9: Row Labels | M9: Sum of Revenue | O9: Row Labels | P9: Pelanggan Aktif
A10: Row Labels | B10: 2020 | C10: 2021 | D10: Grand Total | F10: Blueprints | G10: 16434.51 | I10: DA-SA702 Drone | J10: 67830 | L10: Colorado | M10: 48942.05 | O10: One-time | P10: 684
A11: Jan | B11: 87478.32 | C11: 78479.05 | D11: 165957.37 | F11: eBooks | G11: 58968.41 | I11: DTD-7000 Drone | J11: 76950 | L11: Illinois | M11: 54648.29 | O11: Repeat | P11: 987
A12: Feb | B12: 74764.52 | C12: 72040.18 | D12: 146804.7 | F12: Training Videos | G12: 80716.15 | I12: MICR-564K Drone | J12: 86327 | L12: District of Columbia | M12: 55381.94 | O12: Grand Total | P12: 1671
A13: Mar | B13: 74807.77 | C13: 57080.91 | D13: 131888.68 | F13: Drone Kits | G13: 161242.5 | I13: DTI-84 Drone | J13: 105105 | L13: Ohio | M13: 55575.49
A14: Apr | B14: 66986.64 | C14: 71467.02 | D14: 138453.66 | F14: Robot Kits | G14: 216437 | I14: RXW-9807 Robot | J14: 113810 | L14: Virginia | M14: 58312.21
A15: Mei | B15: 79071.5 | C15: 68308.81 | D15: 147380.31 | F15: Drones | G15: 477447 | I15: RCB-889 Robot | J15: 114192 | L15: Pennsylvania | M15: 61034.69
A16: Jun | B16: 64301.64 | C16: 95401.53 | D16: 159703.17 | F16: Robots | G16: 743505 | I16: RQTE-554 Robot | J16: 116280 | L16: New York | M16: 93019.19
A17: Jul | B17: 76299.55 | C17: 56720.86 | D17: 133020.41 | F17: Grand Total | G17: 1754750.6 | I17: RLK-9920 Robot | J17: 120927 | L17: Florida | M17: 121018.31
A18: Agu | B18: 85316.33 | C18: 76127.18 | D18: 161443.51 | I18: RWW-75 Robot | J18: 120971 | L18: Texas | M18: 196228.76
A19: Sep | B19: 85870.99 | C19: 78851.44 | D19: 164722.43 | I19: MICR-23K Robot | J19: 157325 | L19: California | M19: 237295.59
A20: Okt | B20: 74144.48 | C20: 52348.49 | D20: 126492.97 | I20: Grand Total | J20: 1079717 | L20: Grand Total | M20: 981456.52
A21: Nov | B21: 71137.25 | C21: 62073.12 | D21: 133210.37
A22: Des | B22: 73031.1 | C22: 72641.89 | D22: 145672.99
A23: Grand Total | B23: 913210.09 | C23: 841540.48 | D23: 1754750.6

Sheet Data
A1: OrderID | B1: Date | C1: CustomerID | D1: ProdNumber | E1: Quantity | F1: ProdName | G1: Price | H1: CategoryID | I1: Category | J1: Revenue | K1: Year | L1: MonthNo | M1: Bulan | N1: State | O1: CustomerType
A2: 1 | B2: 43831 | C2: 1866 | D2: EB514 | E2: 2 | F2: =INDEX(tblProduct[ProdName],MATCH(tblData[[#This Row],[ProdNumber]],tblProduct[ProdNumber],0)) -> Polar Robots | G2: =INDEX(tblProduct[Price],MATCH(tblData[[#This Row],[ProdNumber]],tblProduct[ProdNumber],0)) -> 23.99 | H2: =INDEX(tblProduct[Category],MATCH(tblData[[#This Row],[ProdNumber]],tblProduct[ProdNumber],0)) -> 4 | I2: =INDEX(tblCategory[CategoryName],MATCH(tblData[[#This Row],[CategoryID]],tblCategory[CategoryID],0)) -> eBooks | J2: =tblData[[#This Row],[Quantity]]*tblData[[#This Row],[Price]] -> 47.98 | K2: =YEAR(tblData[[#This Row],[Date]]) -> 2020 | L2: =MONTH(tblData[[#This Row],[Date]]) -> 1 | M2: =CHOOSE(tblData[[#This Row],[MonthNo]],"Jan","Feb","Mar","Apr","Mei","Jun","Jul","Agu","Sep","Okt","Nov","Des") -> Jan | N2: =INDEX(tblCustomers[CustomerState],MATCH(tblData[[#This Row],[CustomerID]],tblCustomers[CustomerID],0)) -> Mississippi | O2: =IF(COUNTIF(tblData[CustomerID],tblData[[#This Row],[CustomerID]])>1,"Repeat","One-time") -> One-time
A3: 2 | B3: 43831 | C3: 1567 | D3: RS706 | E3: 3 | F3: =INDEX(tblProduct[ProdName],MATCH(tblData[[#This Row],[ProdNumber]],tblProduct[ProdNumber],0)) -> RWW-75 Robot | G3: =INDEX(tblProduct[Price],MATCH(tblData[[#This Row],[ProdNumber]],tblProduct[ProdNumber],0)) -> 883 | H3: =INDEX(tblProduct[Category],MATCH(tblData[[#This Row],[ProdNumber]],tblProduct[ProdNumber],0)) -> 6 | I3: =INDEX(tblCategory[CategoryName],MATCH(tblData[[#This Row],[CategoryID]],tblCategory[CategoryID],0)) -> Robots | J3: =tblData[[#This Row],[Quantity]]*tblData[[#This Row],[Price]] -> 2649 | K3: =YEAR(tblData[[#This Row],[Date]]) -> 2020 | L3: =MONTH(tblData[[#This Row],[Date]]) -> 1 | M3: =CHOOSE(tblData[[#This Row],[MonthNo]],"Jan","Feb","Mar","Apr","Mei","Jun","Jul","Agu","Sep","Okt","Nov","Des") -> Jan | N3: =INDEX(tblCustomers[CustomerState],MATCH(tblData[[#This Row],[CustomerID]],tblCustomers[CustomerID],0)) -> Texas | O3: =IF(COUNTIF(tblData[CustomerID],tblData[[#This Row],[CustomerID]])>1,"Repeat","One-time") -> One-time
A4: 3 | B4: 43831 | C4: 2064 | D4: TV804 | E4: 6 | F4: =INDEX(tblProduct[ProdName],MATCH(tblData[[#This Row],[ProdNumber]],tblProduct[ProdNumber],0)) -> Drone Video Techniques | G4: =INDEX(tblProduct[Price],MATCH(tblData[[#This Row],[ProdNumber]],tblProduct[ProdNumber],0)) -> 37.99 | H4: =INDEX(tblProduct[Category],MATCH(tblData[[#This Row],[ProdNumber]],tblProduct[ProdNumber],0)) -> 7 | I4: =INDEX(tblCategory[CategoryName],MATCH(tblData[[#This Row],[CategoryID]],tblCategory[CategoryID],0)) -> Training Videos | J4: =tblData[[#This Row],[Quantity]]*tblData[[#This Row],[Price]] -> 227.94 | K4: =YEAR(tblData[[#This Row],[Date]]) -> 2020 | L4: =MONTH(tblData[[#This Row],[Date]]) -> 1 | M4: =CHOOSE(tblData[[#This Row],[MonthNo]],"Jan","Feb","Mar","Apr","Mei","Jun","Jul","Agu","Sep","Okt","Nov","Des") -> Jan | N4: =INDEX(tblCustomers[CustomerState],MATCH(tblData[[#This Row],[CustomerID]],tblCustomers[CustomerID],0)) -> Florida | O4: =IF(COUNTIF(tblData[CustomerID],tblData[[#This Row],[CustomerID]])>1,"Repeat","One-time") -> Repeat
A5: 4 | B5: 43831 | C5: 287 | D5: DK203 | E5: 1 | F5: =INDEX(tblProduct[ProdName],MATCH(tblData[[#This Row],[ProdNumber]],tblProduct[ProdNumber],0)) -> BYOD-220 | G5: =INDEX(tblProduct[Price],MATCH(tblData[[#This Row],[ProdNumber]],tblProduct[ProdNumber],0)) -> 69 | H5: =INDEX(tblProduct[Category],MATCH(tblData[[#This Row],[ProdNumber]],tblProduct[ProdNumber],0)) -> 2 | I5: =INDEX(tblCategory[CategoryName],MATCH(tblData[[#This Row],[CategoryID]],tblCategory[CategoryID],0)) -> Drone Kits | J5: =tblData[[#This Row],[Quantity]]*tblData[[#This Row],[Price]] -> 69 | K5: =YEAR(tblData[[#This Row],[Date]]) -> 2020 | L5: =MONTH(tblData[[#This Row],[Date]]) -> 1 | M5: =CHOOSE(tblData[[#This Row],[MonthNo]],"Jan","Feb","Mar","Apr","Mei","Jun","Jul","Agu","Sep","Okt","Nov","Des") -> Jan | N5: =INDEX(tblCustomers[CustomerState],MATCH(tblData[[#This Row],[CustomerID]],tblCustomers[CustomerID],0)) -> Hawaii | O5: =IF(COUNTIF(tblData[CustomerID],tblData[[#This Row],[CustomerID]])>1,"Repeat","One-time") -> Repeat
A6: 5 | B6: 43831 | C6: 422 | D6: EB517 | E6: 5 | F6: =INDEX(tblProduct[ProdName],MATCH(tblData[[#This Row],[ProdNumber]],tblProduct[ProdNumber],0)) -> SCARA Robots | G6: =INDEX(tblProduct[Price],MATCH(tblData[[#This Row],[ProdNumber]],tblProduct[ProdNumber],0)) -> 19.5 | H6: =INDEX(tblProduct[Category],MATCH(tblData[[#This Row],[ProdNumber]],tblProduct[ProdNumber],0)) -> 4 | I6: =INDEX(tblCategory[CategoryName],MATCH(tblData[[#This Row],[CategoryID]],tblCategory[CategoryID],0)) -> eBooks | J6: =tblData[[#This Row],[Quantity]]*tblData[[#This Row],[Price]] -> 97.5 | K6: =YEAR(tblData[[#This Row],[Date]]) -> 2020 | L6: =MONTH(tblData[[#This Row],[Date]]) -> 1 | M6: =CHOOSE(tblData[[#This Row],[MonthNo]],"Jan","Feb","Mar","Apr","Mei","Jun","Jul","Agu","Sep","Okt","Nov","Des") -> Jan | N6: =INDEX(tblCustomers[CustomerState],MATCH(tblData[[#This Row],[CustomerID]],tblCustomers[CustomerID],0)) -> Iowa | O6: =IF(COUNTIF(tblData[CustomerID],tblData[[#This Row],[CustomerID]])>1,"Repeat","One-time") -> Repeat
A7: 6 | B7: 43831 | C7: 954 | D7: EB519 | E7: 5 | F7: =INDEX(tblProduct[ProdName],MATCH(tblData[[#This Row],[ProdNumber]],tblProduct[ProdNumber],0)) -> Spherical Robots | G7: =INDEX(tblProduct[Price],MATCH(tblData[[#This Row],[ProdNumber]],tblProduct[ProdNumber],0)) -> 16.75 | H7: =INDEX(tblProduct[Category],MATCH(tblData[[#This Row],[ProdNumber]],tblProduct[ProdNumber],0)) -> 4 | I7: =INDEX(tblCategory[CategoryName],MATCH(tblData[[#This Row],[CategoryID]],tblCategory[CategoryID],0)) -> eBooks | J7: =tblData[[#This Row],[Quantity]]*tblData[[#This Row],[Price]] -> 83.75 | K7: =YEAR(tblData[[#This Row],[Date]]) -> 2020 | L7: =MONTH(tblData[[#This Row],[Date]]) -> 1 | M7: =CHOOSE(tblData[[#This Row],[MonthNo]],"Jan","Feb","Mar","Apr","Mei","Jun","Jul","Agu","Sep","Okt","Nov","Des") -> Jan | N7: =INDEX(tblCustomers[CustomerState],MATCH(tblData[[#This Row],[CustomerID]],tblCustomers[CustomerID],0)) -> Alabama | O7: =IF(COUNTIF(tblData[CustomerID],tblData[[#This Row],[CustomerID]])>1,"Repeat","One-time") -> Repeat
A8: 7 | B8: 43832 | C8: 726 | D8: RK604 | E8: 2 | F8: =INDEX(tblProduct[ProdName],MATCH(tblData[[#This Row],[ProdNumber]],tblProduct[ProdNumber],0)) -> BYOR-2640S | G8: =INDEX(tblProduct[Price],MATCH(tblData[[#This Row],[ProdNumber]],tblProduct[ProdNumber],0)) -> 189 | H8: =INDEX(tblProduct[Category],MATCH(tblData[[#This Row],[ProdNumber]],tblProduct[ProdNumber],0)) -> 5 | I8: =INDEX(tblCategory[CategoryName],MATCH(tblData[[#This Row],[CategoryID]],tblCategory[CategoryID],0)) -> Robot Kits | J8: =tblData[[#This Row],[Quantity]]*tblData[[#This Row],[Price]] -> 378 | K8: =YEAR(tblData[[#This Row],[Date]]) -> 2020 | L8: =MONTH(tblData[[#This Row],[Date]]) -> 1 | M8: =CHOOSE(tblData[[#This Row],[MonthNo]],"Jan","Feb","Mar","Apr","Mei","Jun","Jul","Agu","Sep","Okt","Nov","Des") -> Jan | N8: =INDEX(tblCustomers[CustomerState],MATCH(tblData[[#This Row],[CustomerID]],tblCustomers[CustomerID],0)) -> Texas | O8: =IF(COUNTIF(tblData[CustomerID],tblData[[#This Row],[CustomerID]])>1,"Repeat","One-time") -> Repeat
A9: 8 | B9: 43832 | C9: 1740 | D9: TV810 | E9: 1 | F9: =INDEX(tblProduct[ProdName],MATCH(tblData[[#This Row],[ProdNumber]],tblProduct[ProdNumber],0)) -> Understanding Automation | G9: =INDEX(tblProduct[Price],MATCH(tblData[[#This Row],[ProdNumber]],tblProduct[ProdNumber],0)) -> 44.95 | H9: =INDEX(tblProduct[Category],MATCH(tblData[[#This Row],[ProdNumber]],tblProduct[ProdNumber],0)) -> 7 | I9: =INDEX(tblCategory[CategoryName],MATCH(tblData[[#This Row],[CategoryID]],tblCategory[CategoryID],0)) -> Training Videos | J9: =tblData[[#This Row],[Quantity]]*tblData[[#This Row],[Price]] -> 44.95 | K9: =YEAR(tblData[[#This Row],[Date]]) -> 2020 | L9: =MONTH(tblData[[#This Row],[Date]]) -> 1 | M9: =CHOOSE(tblData[[#This Row],[MonthNo]],"Jan","Feb","Mar","Apr","Mei","Jun","Jul","Agu","Sep","Okt","Nov","Des") -> Jan | N9: =INDEX(tblCustomers[CustomerState],MATCH(tblData[[#This Row],[CustomerID]],tblCustomers[CustomerID],0)) -> California | O9: =IF(COUNTIF(tblData[CustomerID],tblData[[#This Row],[CustomerID]])>1,"Repeat","One-time") -> Repeat
A10: 9 | B10: 43832 | C10: 1652 | D10: TV804 | E10: 2 | F10: =INDEX(tblProduct[ProdName],MATCH(tblData[[#This Row],[ProdNumber]],tblProduct[ProdNumber],0)) -> Drone Video Techniques | G10: =INDEX(tblProduct[Price],MATCH(tblData[[#This Row],[ProdNumber]],tblProduct[ProdNumber],0)) -> 37.99 | H10: =INDEX(tblProduct[Category],MATCH(tblData[[#This Row],[ProdNumber]],tblProduct[ProdNumber],0)) -> 7 | I10: =INDEX(tblCategory[CategoryName],MATCH(tblData[[#This Row],[CategoryID]],tblCategory[CategoryID],0)) -> Training Videos | J10: =tblData[[#This Row],[Quantity]]*tblData[[#This Row],[Price]] -> 75.98 | K10: =YEAR(tblData[[#This Row],[Date]]) -> 2020 | L10: =MONTH(tblData[[#This Row],[Date]]) -> 1 | M10: =CHOOSE(tblData[[#This Row],[MonthNo]],"Jan","Feb","Mar","Apr","Mei","Jun","Jul","Agu","Sep","Okt","Nov","Des") -> Jan | N10: =INDEX(tblCustomers[CustomerState],MATCH(tblData[[#This Row],[CustomerID]],tblCustomers[CustomerID],0)) -> Iowa | O10: =IF(COUNTIF(tblData[CustomerID],tblData[[#This Row],[CustomerID]])>1,"Repeat","One-time") -> One-time
A11: 10 | B11: 43832 | C11: 1431 | D11: DS304 | E11: 2 | F11: =INDEX(tblProduct[ProdName],MATCH(tblData[[#This Row],[ProdNumber]],tblProduct[ProdNumber],0)) -> DTE-QFN20 Drone | G11: =INDEX(tblProduct[Price],MATCH(tblData[[#This Row],[ProdNumber]],tblProduct[ProdNumber],0)) -> 250 | H11: =INDEX(tblProduct[Category],MATCH(tblData[[#This Row],[ProdNumber]],tblProduct[ProdNumber],0)) -> 3 | I11: =INDEX(tblCategory[CategoryName],MATCH(tblData[[#This Row],[CategoryID]],tblCategory[CategoryID],0)) -> Drones | J11: =tblData[[#This Row],[Quantity]]*tblData[[#This Row],[Price]] -> 500 | K11: =YEAR(tblData[[#This Row],[Date]]) -> 2020 | L11: =MONTH(tblData[[#This Row],[Date]]) -> 1 | M11: =CHOOSE(tblData[[#This Row],[MonthNo]],"Jan","Feb","Mar","Apr","Mei","Jun","Jul","Agu","Sep","Okt","Nov","Des") -> Jan | N11: =INDEX(tblCustomers[CustomerState],MATCH(tblData[[#This Row],[CustomerID]],tblCustomers[CustomerID],0)) -> California | O11: =IF(COUNTIF(tblData[CustomerID],tblData[[#This Row],[CustomerID]])>1,"Repeat","One-time") -> One-time
A12: 11 | B12: 43832 | C12: 270 | D12: RK604 | E12: 2 | F12: =INDEX(tblProduct[ProdName],MATCH(tblData[[#This Row],[ProdNumber]],tblProduct[ProdNumber],0)) -> BYOR-2640S | G12: =INDEX(tblProduct[Price],MATCH(tblData[[#This Row],[ProdNumber]],tblProduct[ProdNumber],0)) -> 189 | H12: =INDEX(tblProduct[Category],MATCH(tblData[[#This Row],[ProdNumber]],tblProduct[ProdNumber],0)) -> 5 | I12: =INDEX(tblCategory[CategoryName],MATCH(tblData[[#This Row],[CategoryID]],tblCategory[CategoryID],0)) -> Robot Kits | J12: =tblData[[#This Row],[Quantity]]*tblData[[#This Row],[Price]] -> 378 | K12: =YEAR(tblData[[#This Row],[Date]]) -> 2020 | L12: =MONTH(tblData[[#This Row],[Date]]) -> 1 | M12: =CHOOSE(tblData[[#This Row],[MonthNo]],"Jan","Feb","Mar","Apr","Mei","Jun","Jul","Agu","Sep","Okt","Nov","Des") -> Jan | N12: =INDEX(tblCustomers[CustomerState],MATCH(tblData[[#This Row],[CustomerID]],tblCustomers[CustomerID],0)) -> District of Columbia | O12: =IF(COUNTIF(tblData[CustomerID],tblData[[#This Row],[CustomerID]])>1,"Repeat","One-time") -> One-time
A13: 12 | B13: 43832 | C13: 815 | D13: DK201 | E13: 5 | F13: =INDEX(tblProduct[ProdName],MATCH(tblData[[#This Row],[ProdNumber]],tblProduct[ProdNumber],0)) -> BYOD-100 | G13: =INDEX(tblProduct[Price],MATCH(tblData[[#This Row],[ProdNumber]],tblProduct[ProdNumber],0)) -> 54 | H13: =INDEX(tblProduct[Category],MATCH(tblData[[#This Row],[ProdNumber]],tblProduct[ProdNumber],0)) -> 2 | I13: =INDEX(tblCategory[CategoryName],MATCH(tblData[[#This Row],[CategoryID]],tblCategory[CategoryID],0)) -> Drone Kits | J13: =tblData[[#This Row],[Quantity]]*tblData[[#This Row],[Price]] -> 270 | K13: =YEAR(tblData[[#This Row],[Date]]) -> 2020 | L13: =MONTH(tblData[[#This Row],[Date]]) -> 1 | M13: =CHOOSE(tblData[[#This Row],[MonthNo]],"Jan","Feb","Mar","Apr","Mei","Jun","Jul","Agu","Sep","Okt","Nov","Des") -> Jan | N13: =INDEX(tblCustomers[CustomerState],MATCH(tblData[[#This Row],[CustomerID]],tblCustomers[CustomerID],0)) -> District of Columbia | O13: =IF(COUNTIF(tblData[CustomerID],tblData[[#This Row],[CustomerID]])>1,"Repeat","One-time") -> Repeat
... A3340: 3340 | B3340: 44515 | C3340: 5 | D3340: EB508 | E3340: 2 | F3340: =INDEX(tblProduct[ProdName],MATCH(tblData[[#This Row],[ProdNumber]],tblProduct[ProdNumber],0)) -> Fixed Wing Drones | G3340: =INDEX(tblProduct[Price],MATCH(tblData[[#This Row],[ProdNumber]],tblProduct[ProdNumber],0)) -> 15.5 | H3340: =INDEX(tblProduct[Category],MATCH(tblData[[#This Row],[ProdNumber]],tblProduct[ProdNumber],0)) -> 4 | I3340: =INDEX(tblCategory[CategoryName],MATCH(tblData[[#This Row],[CategoryID]],tblCategory[CategoryID],0)) -> eBooks | J3340: =tblData[[#This Row],[Quantity]]*tblData[[#This Row],[Price]] -> 31 | K3340: =YEAR(tblData[[#This Row],[Date]]) -> 2021 | L3340: =MONTH(tblData[[#This Row],[Date]]) -> 11 | M3340: =CHOOSE(tblData[[#This Row],[MonthNo]],"Jan","Feb","Mar","Apr","Mei","Jun","Jul","Agu","Sep","Okt","Nov","Des") -> Nov | N3340: =INDEX(tblCustomers[CustomerState],MATCH(tblData[[#This Row],[CustomerID]],tblCustomers[CustomerID],0)) -> Texas | O3340: =IF(COUNTIF(tblData[CustomerID],tblData[[#This Row],[CustomerID]])>1,"Repeat","One-time") -> Repeat

Sheet customers
A1: CustomerID | B1: FirstName | C1: LastName | D1: CustomerEmail | E1: CustomerPhone | F1: CustomerAddress | G1: CustomerCity | H1: CustomerState | I1: CustomerZip
A2: 1 | B2: Grazia | C2: Rasmus | D2: grasmusas@i2i.jp#mailto:grasmusas@i2i.jp# | E2: (202) 577-2595 | F2: 628 Buhler Junction | G2: Washington | H2: District of Columbia | I2: 20029
A3: 2 | B3: Bunny | C3: Trevan | D3: btrevanmj@wordpress.org#mailto:btrevanmj@wordpress.org# | E3: 917-903-2827 | F3: 52 Cascade Drive | G3: Jamaica | H3: New York | I3: 11436
A4: 3 | B4: Tracie | C4: Grayston | D4: tgrayston7k@pagesperso-orange.fr#mailto:tgrayston7k@pagesperso-orange.fr# | E4: 404-868-2391 | F4: 672 Comanche Way | G4: Atlanta | H4: Georgia | I4: 30343
A5: 4 | B5: Amerigo | C5: Garrelts | D5: agarrelts6e@oaic.gov.au#mailto:agarrelts6e@oaic.gov.au# | E5: 415-190-3290 | F5: 8252 Village Green Hill | G5: San Francisco | H5: California | I5: 94177
A6: 5 | B6: Shea | C6: Stronghill | D6: sstronghillc1@google.nl#mailto:sstronghillc1@google.nl# | E6: 432-775-7828 | F6: 542 3rd Point | G6: Midland | H6: Texas | I6: 79705
A7: 6 | B7: Geoffry | C7: Bonde | D7: gbonde90@vimeo.com#mailto:gbonde90@vimeo.com# | E7: 415-176-9919 | F7: 781 Larry Place | G7: San Francisco | H7: California | I7: 94159
A8: 7 | B8: Noelle | C8: Carlile | D8: ncarlile37@mit.edu#mailto:ncarlile37@mit.edu# | E8: 405-745-9826 | F8: 539 Crowley Parkway | G8: Oklahoma City | H8: Oklahoma | I8: 73114
A9: 8 | B9: Binny | C9: Whetson | D9: bwhetsonio@amazon.de#mailto:bwhetsonio@amazon.de# | E9: 585-968-0566 | F9: 579 Sugar Circle | G9: Rochester | H9: New York | I9: 14619
A10: 9 | B10: Curran | C10: MacMichael | D10: cmacmichael5y@businesswire.com#mailto:cmacmichael5y@businesswire.com# | E10: 520-968-8763 | F10: 4949 Hauk Road | G10: Tucson | H10: Arizona | I10: 85705
A11: 10 | B11: Andy | C11: Woodruff | D11: awoodruffo@techcrunch.com#mailto:awoodruffo@techcrunch.com# | E11: 315-377-2198 | F11: 8278 Scott Terrace | G11: Rochester | H11: New York | I11: 14614
A12: 11 | B12: Darla | C12: Hassen | D12: dhassencj@hp.com#mailto:dhassencj@hp.com# | E12: 585-418-2593 | F12: 6900 Birchwood Center | G12: Rochester | H12: New York | I12: 14604
A13: 12 | B13: Gerard | C13: Witherdon | D13: gwitherdon8m@ow.ly#mailto:gwitherdon8m@ow.ly# | E13: 405-794-2184 | F13: 27 Golf View Parkway | G13: Norman | H13: Oklahoma | I13: 73071
... A2124: 2123 | B2124: Morissa | C2124: Vasic | D2124: mvasiclp@sourceforge.net#mailto:mvasiclp@sourceforge.net# | E2124: 727-419-6625 | F2124: 49 Susan Avenue | G2124: Saint Petersburg | H2124: Florida | I2124: 33705

Sheet orders
A1: OrderID | B1: Date | C1: CustomerID | D1: ProdNumber | E1: Quantity
A2: 1 | B2: 43831 | C2: 1866 | D2: EB514 | E2: 2
A3: 2 | B3: 43831 | C3: 1567 | D3: RS706 | E3: 3
A4: 3 | B4: 43831 | C4: 2064 | D4: TV804 | E4: 6
A5: 4 | B5: 43831 | C5: 287 | D5: DK203 | E5: 1
A6: 5 | B6: 43831 | C6: 422 | D6: EB517 | E6: 5
A7: 6 | B7: 43831 | C7: 954 | D7: EB519 | E7: 5
A8: 7 | B8: 43832 | C8: 726 | D8: RK604 | E8: 2
A9: 8 | B9: 43832 | C9: 1740 | D9: TV810 | E9: 1
A10: 9 | B10: 43832 | C10: 1652 | D10: TV804 | E10: 2
A11: 10 | B11: 43832 | C11: 1431 | D11: DS304 | E11: 2
A12: 11 | B12: 43832 | C12: 270 | D12: RK604 | E12: 2
A13: 12 | B13: 43832 | C13: 815 | D13: DK201 | E13: 5
... A3340: 3340 | B3340: 44515 | C3340: 5 | D3340: EB508 | E3340: 2

Sheet product category
A1: CategoryID | B1: CategoryName | C1: CategoryAbbreviation
A2: 1 | B2: Blueprints | C2: BP
A3: 2 | B3: Drone Kits | C3: DK
A4: 3 | B4: Drones | C4: DS
A5: 4 | B5: eBooks | C5: EB
A6: 5 | B6: Robot Kits | C6: RK
A7: 6 | B7: Robots | C7: RS
A8: 7 | B8: Training Videos | C8: TV

Sheet product
A1: ProdNumber | B1: ProdName | C1: Category | D1: Price
A2: BP101 | B2: All Eyes Drone Blueprint | C2: 1 | D2: 9.99
A3: BP102 | B3: Bsquare Robot Blueprint | C3: 1 | D3: 8.99
A4: BP104 | B4: Cat Robot Blueprint | C4: 1 | D4: 4.99
A5: BP105 | B5: Creature Robot Arms Blueprint | C5: 1 | D5: 12
A6: BP106 | B6: Hexacopter Drone Blueprint | C6: 1 | D6: 8.99
A7: BP107 | B7: Ladybug Robot Blueprint | C7: 1 | D7: 12
A8: BP108 | B8: Panda Robot Blueprint | C8: 1 | D8: 7.99
A9: BP109 | B9: QuadroCopter Blueprint | C9: 1 | D9: 10.99
A10: BP110 | B10: Sleepy Eye Blueprint | C10: 1 | D10: 11.99
A11: BP111 | B11: Upside Down Robot Blueprint | C11: 1 | D11: 12
A12: DK201 | B12: BYOD-100 | C12: 2 | D12: 54
A13: DK202 | B13: BYOD-200 | C13: 2 | D13: 58.95
... A71: TV813 | B71: Virtual Reality Basics | C71: 7 | D71: 29.99
